{
  "name": "@iqvizyonui/react-teaching-popover",
  "entries": [
    {
      "date": "Wed, 22 Jul 2026 14:27:18 GMT",
      "tag": "@iqvizyonui/react-teaching-popover_v9.8.1",
      "version": "9.8.1",
      "comments": {
        "patch": [
          {
            "author": "issakaibrahimrayamah@gmail.com",
            "package": "@iqvizyonui/react-teaching-popover",
            "commit": "not available",
            "comment": "chore: refresh repository links and package metadata"
          },
          {
            "author": "beachball",
            "package": "@iqvizyonui/react-teaching-popover",
            "comment": "Bump @iqvizyonui/react-jsx-runtime to v9.4.6",
            "commit": "d5fd84158c4f49617b3cea859d66df7d91f86b04"
          },
          {
            "author": "beachball",
            "package": "@iqvizyonui/react-teaching-popover",
            "comment": "Bump @iqvizyonui/react-theme to v9.2.3",
            "commit": "d5fd84158c4f49617b3cea859d66df7d91f86b04"
          },
          {
            "author": "beachball",
            "package": "@iqvizyonui/react-teaching-popover",
            "comment": "Bump @iqvizyonui/react-utilities to v9.27.1",
            "commit": "d5fd84158c4f49617b3cea859d66df7d91f86b04"
          },
          {
            "author": "beachball",
            "package": "@iqvizyonui/react-teaching-popover",
            "comment": "Bump @iqvizyonui/react-shared-contexts to v9.26.4",
            "commit": "d5fd84158c4f49617b3cea859d66df7d91f86b04"
          },
          {
            "author": "beachball",
            "package": "@iqvizyonui/react-teaching-popover",
            "comment": "Bump @iqvizyonui/react-popover to v9.15.1",
            "commit": "d5fd84158c4f49617b3cea859d66df7d91f86b04"
          },
          {
            "author": "beachball",
            "package": "@iqvizyonui/react-teaching-popover",
            "comment": "Bump @iqvizyonui/react-button to v9.10.3",
            "commit": "d5fd84158c4f49617b3cea859d66df7d91f86b04"
          },
          {
            "author": "beachball",
            "package": "@iqvizyonui/react-teaching-popover",
            "comment": "Bump @iqvizyonui/react-tabster to v9.26.18",
            "commit": "d5fd84158c4f49617b3cea859d66df7d91f86b04"
          },
          {
            "author": "beachball",
            "package": "@iqvizyonui/react-teaching-popover",
            "comment": "Bump @iqvizyonui/react-aria to v9.17.15",
            "commit": "d5fd84158c4f49617b3cea859d66df7d91f86b04"
          },
          {
            "author": "beachball",
            "package": "@iqvizyonui/react-teaching-popover",
            "comment": "Bump @iqvizyonui/react-context-selector to v9.2.20",
            "commit": "d5fd84158c4f49617b3cea859d66df7d91f86b04"
          }
        ]
      }
    },
    {
      "date": "Fri, 17 Jul 2026 09:54:16 GMT",
      "tag": "@iqvizyonui/react-teaching-popover_v9.8.0",
      "version": "9.8.0",
      "comments": {
        "minor": [
          {
            "author": "noreply@iqvizyon.com",
            "package": "@iqvizyonui/react-teaching-popover",
            "commit": "02149189a177ccd9e545d3e2780488a68dc7a682",
            "comment": "feat: rebrand Fluent naming to Iqvizyon with iqv custom element prefix"
          },
          {
            "author": "beachball",
            "package": "@iqvizyonui/react-teaching-popover",
            "comment": "Bump @iqvizyonui/react-jsx-runtime to v9.4.5",
            "commit": "1b5eaaff6e870febb52691f53fc15a8c7feaa71b"
          },
          {
            "author": "beachball",
            "package": "@iqvizyonui/react-teaching-popover",
            "comment": "Bump @iqvizyonui/react-theme to v9.2.2",
            "commit": "1b5eaaff6e870febb52691f53fc15a8c7feaa71b"
          },
          {
            "author": "beachball",
            "package": "@iqvizyonui/react-teaching-popover",
            "comment": "Bump @iqvizyonui/react-utilities to v9.27.0",
            "commit": "1b5eaaff6e870febb52691f53fc15a8c7feaa71b"
          },
          {
            "author": "beachball",
            "package": "@iqvizyonui/react-teaching-popover",
            "comment": "Bump @iqvizyonui/react-shared-contexts to v9.26.3",
            "commit": "1b5eaaff6e870febb52691f53fc15a8c7feaa71b"
          },
          {
            "author": "beachball",
            "package": "@iqvizyonui/react-teaching-popover",
            "comment": "Bump @iqvizyonui/react-popover to v9.15.0",
            "commit": "1b5eaaff6e870febb52691f53fc15a8c7feaa71b"
          },
          {
            "author": "beachball",
            "package": "@iqvizyonui/react-teaching-popover",
            "comment": "Bump @iqvizyonui/react-button to v9.10.2",
            "commit": "1b5eaaff6e870febb52691f53fc15a8c7feaa71b"
          },
          {
            "author": "beachball",
            "package": "@iqvizyonui/react-teaching-popover",
            "comment": "Bump @iqvizyonui/react-tabster to v9.26.17",
            "commit": "1b5eaaff6e870febb52691f53fc15a8c7feaa71b"
          },
          {
            "author": "beachball",
            "package": "@iqvizyonui/react-teaching-popover",
            "comment": "Bump @iqvizyonui/react-aria to v9.17.14",
            "commit": "1b5eaaff6e870febb52691f53fc15a8c7feaa71b"
          },
          {
            "author": "beachball",
            "package": "@iqvizyonui/react-teaching-popover",
            "comment": "Bump @iqvizyonui/react-context-selector to v9.2.19",
            "commit": "1b5eaaff6e870febb52691f53fc15a8c7feaa71b"
          }
        ]
      }
    }
  ]
}
